sitemap_markitdown/__init__.py
sitemap_markitdown/cli.py
sitemap_markitdown/sitemap_parser.py
sitemap_markitdown-0.1.0.dist-info/METADATA
sitemap_markitdown-0.1.0.dist-info/WHEEL
sitemap_markitdown-0.1.0.dist-info/entry_points.txt
sitemap_markitdown-0.1.0.dist-info/licenses/LICENSE
sitemap_markitdown-0.1.0.dist-info/RECORD
