Metadata-Version: 2.4
Name: sitemap-markitdown
Version: 0.1.0
Summary: A comprehensive toolkit for parsing sitemaps and converting web content to Markdown
Project-URL: Homepage, https://gitlab.com/thomas.pedot1/sitemap-markitdown
Project-URL: Issues, https://gitlab.com/thomas.pedot1/sitemap-markitdown/issues
License-Expression: MIT
License-File: LICENSE
Classifier: Development Status :: 3 - Alpha
Classifier: Environment :: Console
Classifier: License :: OSI Approved :: MIT License
Classifier: Operating System :: OS Independent
Classifier: Programming Language :: Python :: 3
Classifier: Programming Language :: Python :: 3.8
Classifier: Programming Language :: Python :: 3.9
Classifier: Programming Language :: Python :: 3.10
Classifier: Programming Language :: Python :: 3.11
Classifier: Topic :: Internet :: WWW/HTTP :: Site Management
Classifier: Topic :: Text Processing :: Markup :: Markdown
Requires-Python: >=3.8
Requires-Dist: click>=8.1.8
Requires-Dist: lxml>=5.3.0
Requires-Dist: markitdown>=0.0.1a3
Requires-Dist: tqdm>=4.67.1
Provides-Extra: dev
Requires-Dist: pytest-cov>=4.1.0; extra == 'dev'
Requires-Dist: pytest>=7.4.0; extra == 'dev'
Provides-Extra: llm
Requires-Dist: openai>=1.0.0; extra == 'llm'
